bracketool/__init__.py
bracketool/brackets.py
bracketool/domain.py
bracketool/elorating.py
bracketool/entities.py
bracketool/pairings.py
bracketool/single_elimination.py
bracketool/teambrackets.py
bracketool-0.1.dist-info/LICENSE
bracketool-0.1.dist-info/METADATA
bracketool-0.1.dist-info/WHEEL
bracketool-0.1.dist-info/top_level.txt
bracketool-0.1.dist-info/RECORD
